gehomesdk/__init__.py
gehomesdk/entry_points.py
gehomesdk/gather_data.py
gehomesdk/ge_appliance.py
gehomesdk/clients/__init__.py
gehomesdk/clients/async_helpers.py
gehomesdk/clients/async_login_flows.py
gehomesdk/clients/base_client.py
gehomesdk/clients/const.py
gehomesdk/clients/states.py
gehomesdk/clients/websocket_client.py
gehomesdk/erd/__init__.py
gehomesdk/erd/erd_code_class.py
gehomesdk/erd/erd_codes.py
gehomesdk/erd/erd_configuration.py
gehomesdk/erd/erd_data_type.py
gehomesdk/erd/erd_encoder.py
gehomesdk/erd/converters/__init__.py
gehomesdk/erd/converters/abstract.py
gehomesdk/erd/converters/ac/__init__.py
gehomesdk/erd/converters/ac/erd_ac_available_fan_speeds_converter.py
gehomesdk/erd/converters/ac/erd_ac_available_modes_converter.py
gehomesdk/erd/converters/ac/erd_ac_available_turbo_quiet_modes_converter.py
gehomesdk/erd/converters/ac/erd_ac_fan_setting_converter.py
gehomesdk/erd/converters/ac/erd_ac_filter_status_converter.py
gehomesdk/erd/converters/ac/erd_ac_operation_mode_converter.py
gehomesdk/erd/converters/ac/erd_ac_target_temperature_converter.py
gehomesdk/erd/converters/ac/erd_ac_turbo_quiet_mode_converter.py
gehomesdk/erd/converters/ac/erd_sac_available_modes_converter.py
gehomesdk/erd/converters/ac/erd_sac_target_temperature_range_converter.py
gehomesdk/erd/converters/ac/erd_wac_demand_response_power_converter.py
gehomesdk/erd/converters/ac/erd_wac_demand_response_state_converter.py
gehomesdk/erd/converters/advantium/__init__.py
gehomesdk/erd/converters/advantium/erd_advantium_cook_setting_converter.py
gehomesdk/erd/converters/advantium/erd_advantium_cook_status_converter.py
gehomesdk/erd/converters/advantium/erd_advantium_cook_time_adjust_converter.py
gehomesdk/erd/converters/advantium/erd_advantium_cook_time_min_max_converter.py
gehomesdk/erd/converters/advantium/erd_advantium_cook_time_remaining_converter.py
gehomesdk/erd/converters/advantium/erd_advantium_kitchen_timer_min_max_converter.py
gehomesdk-2025.11.0.dist-info/LICENSE
gehomesdk-2025.11.0.dist-info/METADATA
gehomesdk-2025.11.0.dist-info/WHEEL
gehomesdk-2025.11.0.dist-info/entry_points.txt
gehomesdk-2025.11.0.dist-info/top_level.txt
gehomesdk-2025.11.0.dist-info/RECORD
