Metadata-Version: 2.2
Name: gehomesdk
Version: 2025.11.0
Summary: Python SDK for GE Home Appliances
Home-page: https://github.com/simbaja/gehome
Author: Jack Simbach
Author-email: jack.simbach@gmail.com
License: MIT
Classifier: License :: OSI Approved :: MIT License
Classifier: Programming Language :: Python :: 3
Classifier: Programming Language :: Python :: 3.13
License-File: LICENSE
Requires-Dist: aiohttp>=3.13.0
Requires-Dist: bidict
Requires-Dist: requests>=2.32.4
Requires-Dist: websockets>=15.0.0
Requires-Dist: humanize
Requires-Dist: beautifulsoup4>=4.13.1
Dynamic: author
Dynamic: author-email
Dynamic: classifier
Dynamic: description
Dynamic: description-content-type
Dynamic: home-page
Dynamic: license
Dynamic: requires-dist
Dynamic: summary
